odoo/addons/fleet_vehicle_notebook/README.rst
odoo/addons/fleet_vehicle_notebook/__init__.py
odoo/addons/fleet_vehicle_notebook/__manifest__.py
odoo/addons/fleet_vehicle_notebook/i18n/fleet_vehicle_notebook.pot
odoo/addons/fleet_vehicle_notebook/i18n/it.po
odoo/addons/fleet_vehicle_notebook/i18n/pt_BR.po
odoo/addons/fleet_vehicle_notebook/readme/CONTRIBUTORS.rst
odoo/addons/fleet_vehicle_notebook/readme/CREDITS.rst
odoo/addons/fleet_vehicle_notebook/readme/DESCRIPTION.rst
odoo/addons/fleet_vehicle_notebook/static/description/banner.png
odoo/addons/fleet_vehicle_notebook/static/description/icon.png
odoo/addons/fleet_vehicle_notebook/static/description/index.html
odoo/addons/fleet_vehicle_notebook/views/fleet_vehicle.xml
odoo12_addon_fleet_vehicle_notebook-12.0.1.0.0.99.dev6.dist-info/METADATA
odoo12_addon_fleet_vehicle_notebook-12.0.1.0.0.99.dev6.dist-info/WHEEL
odoo12_addon_fleet_vehicle_notebook-12.0.1.0.0.99.dev6.dist-info/top_level.txt
odoo12_addon_fleet_vehicle_notebook-12.0.1.0.0.99.dev6.dist-info/RECORD
